{
  "Posts": [
    {
      "FileName": "third-post.md",
      "Title": "Third Post",
      "Date": "2025-01-01T12:00:00",
      "Tags": [
        "test",
        "hello"
      ],
      "Content": "---\r\ntitle: \u0022Third Post\u0022\r\ndate: 2025-01-01 12:00:00\r\ntags: [test, hello]\r\n---\r\n\r\n\r\n# Headers\r\n\r\n\u0060\u0060\u0060\r\n# h1 Heading 8-)\r\n## h2 Heading\r\n### h3 Heading\r\n#### h4 Heading\r\n##### h5 Heading\r\n###### h6 Heading\r\n\r\nAlternatively, for H1 and H2, an underline-ish style:\r\n\r\nAlt-H1\r\n======\r\n\r\nAlt-H2\r\n------\r\n\u0060\u0060\u0060\t\r\n\r\n# h1 Heading 8-)\r\n## h2 Heading\r\n### h3 Heading\r\n#### h4 Heading\r\n##### h5 Heading\r\n###### h6 Heading\r\n\r\nAlternatively, for H1 and H2, an underline-ish style:\r\n\r\nAlt-H1\r\n======\r\n\r\nAlt-H2\r\n------\r\n\r\n------\r\n\r\n# Emphasis\r\n\r\n\u0060\u0060\u0060\r\nEmphasis, aka italics, with *asterisks* or _underscores_.\r\n\r\nStrong emphasis, aka bold, with **asterisks** or __underscores__.\r\n\r\nCombined emphasis with **asterisks and _underscores_**.\r\n\r\nStrikethrough uses two tildes. ~~Scratch this.~~\r\n\r\n**This is bold text**\r\n\r\n__This is bold text__\r\n\r\n*This is italic text*\r\n\r\n_This is italic text_\r\n\r\n~~Strikethrough~~\r\n\u0060\u0060\u0060\r\n\r\nEmphasis, aka italics, with *asterisks* or _underscores_.\r\n\r\nStrong emphasis, aka bold, with **asterisks** or __underscores__.\r\n\r\nCombined emphasis with **asterisks and _underscores_**.\r\n\r\nStrikethrough uses two tildes. ~~Scratch this.~~\r\n\r\n**This is bold text**\r\n\r\n__This is bold text__\r\n\r\n*This is italic text*\r\n\r\n_This is italic text_\r\n\r\n~~Strikethrough~~\r\n\r\n------\r\n\r\n# Lists\r\n\r\n\u0060\u0060\u0060\r\n1. First ordered list item\r\n2. Another item\r\n\u22C5\u22C5* Unordered sub-list.\r\n1. Actual numbers don\u0027t matter, just that it\u0027s a number\r\n\u22C5\u22C51. Ordered sub-list\r\n4. And another item.\r\n\r\n\u22C5\u22C5\u22C5You can have properly indented paragraphs within list items. Notice the blank line above, and the leading spaces (at least one, but we\u0027ll use three here to also align the raw Markdown).\r\n\r\n\u22C5\u22C5\u22C5To have a line break without a paragraph, you will need to use two trailing spaces.\u22C5\u22C5\r\n\u22C5\u22C5\u22C5Note that this line is separate, but within the same paragraph.\u22C5\u22C5\r\n\u22C5\u22C5\u22C5(This is contrary to the typical GFM line break behaviour, where trailing spaces are not required.)\r\n\r\n* Unordered list can use asterisks\r\n- Or minuses\r\n\u002B Or pluses\r\n\r\n1. Make my changes\r\n    1. Fix bug\r\n    2. Improve formatting\r\n        - Make the headings bigger\r\n2. Push my commits to GitHub\r\n3. Open a pull request\r\n    * Describe my changes\r\n    * Mention all the members of my team\r\n        * Ask for feedback\r\n\r\n\u002B Create a list by starting a line with \u0060\u002B\u0060, \u0060-\u0060, or \u0060*\u0060\r\n\u002B Sub-lists are made by indenting 2 spaces:\r\n  - Marker character change forces new list start:\r\n    * Ac tristique libero volutpat at\r\n    \u002B Facilisis in pretium nisl aliquet\r\n    - Nulla volutpat aliquam velit\r\n\u002B Very easy!\r\n\u0060\u0060\u0060\r\n\r\n1. First ordered list item\r\n2. Another item\r\n\u22C5\u22C5* Unordered sub-list.\r\n1. Actual numbers don\u0027t matter, just that it\u0027s a number\r\n\u22C5\u22C51. Ordered sub-list\r\n4. And another item.\r\n\r\n\u22C5\u22C5\u22C5You can have properly indented paragraphs within list items. Notice the blank line above, and the leading spaces (at least one, but we\u0027ll use three here to also align the raw Markdown).\r\n\r\n\u22C5\u22C5\u22C5To have a line break without a paragraph, you will need to use two trailing spaces.\u22C5\u22C5\r\n\u22C5\u22C5\u22C5Note that this line is separate, but within the same paragraph.\u22C5\u22C5\r\n\u22C5\u22C5\u22C5(This is contrary to the typical GFM line break behaviour, where trailing spaces are not required.)\r\n\r\n* Unordered list can use asterisks\r\n- Or minuses\r\n\u002B Or pluses\r\n\r\n1. Make my changes\r\n    1. Fix bug\r\n    2. Improve formatting\r\n        - Make the headings bigger\r\n2. Push my commits to GitHub\r\n3. Open a pull request\r\n    * Describe my changes\r\n    * Mention all the members of my team\r\n        * Ask for feedback\r\n\r\n\u002B Create a list by starting a line with \u0060\u002B\u0060, \u0060-\u0060, or \u0060*\u0060\r\n\u002B Sub-lists are made by indenting 2 spaces:\r\n  - Marker character change forces new list start:\r\n    * Ac tristique libero volutpat at\r\n    \u002B Facilisis in pretium nisl aliquet\r\n    - Nulla volutpat aliquam velit\r\n\u002B Very easy!\r\n\r\n------\r\n\r\n# Task lists\r\n\r\n\u0060\u0060\u0060\r\n- [x] Finish my changes\r\n- [ ] Push my commits to GitHub\r\n- [ ] Open a pull request\r\n- [x] @mentions, #refs, [links](), **formatting**, and \u003Cdel\u003Etags\u003C/del\u003E supported\r\n- [x] list syntax required (any unordered or ordered list supported)\r\n- [x] this is a complete item\r\n- [ ] this is an incomplete item\r\n\u0060\u0060\u0060\r\n\r\n- [x] Finish my changes\r\n- [ ] Push my commits to GitHub\r\n- [ ] Open a pull request\r\n- [x] @mentions, #refs, [links](), **formatting**, and \u003Cdel\u003Etags\u003C/del\u003E supported\r\n- [x] list syntax required (any unordered or ordered list supported)\r\n- [ ] this is a complete item\r\n- [ ] this is an incomplete item\r\n\r\n------\r\n\r\n# Ignoring Markdown formatting\r\n\r\nYou can tell GitHub to ignore (or escape) Markdown formatting by using \\ before the Markdown character.\r\n\r\n\u0060\u0060\u0060\r\nLet\u0027s rename \\*our-new-project\\* to \\*our-old-project\\*.\r\n\u0060\u0060\u0060\r\n\r\nLet\u0027s rename \\*our-new-project\\* to \\*our-old-project\\*.\r\n\r\n------\r\n\r\n# Links\r\n\r\n\u0060\u0060\u0060\r\n[I\u0027m an inline-style link](https://www.google.com)\r\n\r\n[I\u0027m an inline-style link with title](https://www.google.com \u0022Google\u0027s Homepage\u0022)\r\n\r\n[I\u0027m a reference-style link][Arbitrary case-insensitive reference text]\r\n\r\n[I\u0027m a relative reference to a repository file](../blob/master/LICENSE)\r\n\r\n[You can use numbers for reference-style link definitions][1]\r\n\r\nOr leave it empty and use the [link text itself].\r\n\r\nURLs and URLs in angle brackets will automatically get turned into links.\r\nhttp://www.example.com or \u003Chttp://www.example.com\u003E and sometimes\r\nexample.com (but not on Github, for example).\r\n\r\nSome text to show that the reference links can follow later.\r\n\r\n[arbitrary case-insensitive reference text]: https://www.mozilla.org\r\n[1]: http://slashdot.org\r\n[link text itself]: http://www.reddit.com\r\n\u0060\u0060\u0060\r\n\r\n[I\u0027m an inline-style link](https://www.google.com)\r\n\r\n[I\u0027m an inline-style link with title](https://www.google.com \u0022Google\u0027s Homepage\u0022)\r\n\r\n[I\u0027m a reference-style link][Arbitrary case-insensitive reference text]\r\n\r\n[I\u0027m a relative reference to a repository file](../blob/master/LICENSE)\r\n\r\n[You can use numbers for reference-style link definitions][1]\r\n\r\nOr leave it empty and use the [link text itself].\r\n\r\nURLs and URLs in angle brackets will automatically get turned into links.\r\nhttp://www.example.com or \u003Chttp://www.example.com\u003E and sometimes\r\nexample.com (but not on Github, for example).\r\n\r\nSome text to show that the reference links can follow later.\r\n\r\n[arbitrary case-insensitive reference text]: https://www.mozilla.org\r\n[1]: http://slashdot.org\r\n[link text itself]: http://www.reddit.com\r\n\r\n------\r\n\r\n# Images\r\n\r\n\u0060\u0060\u0060\r\nHere\u0027s our logo (hover to see the title text):\r\n\r\nInline-style:\r\n![alt text](https://github.com/adam-p/markdown-here/raw/master/src/common/images/icon48.png \u0022Logo Title Text 1\u0022)\r\n\r\nReference-style:\r\n![alt text][logo]\r\n\r\n[logo]: https://github.com/adam-p/markdown-here/raw/master/src/common/images/icon48.png \u0022Logo Title Text 2\u0022\r\n\r\n![Minion](https://octodex.github.com/images/minion.png)\r\n![Stormtroopocat](https://octodex.github.com/images/stormtroopocat.jpg \u0022The Stormtroopocat\u0022)\r\n\r\nLike links, Images also have a footnote style syntax\r\n\r\n![Alt text][id]\r\n\r\nWith a reference later in the document defining the URL location:\r\n\r\n[id]: https://octodex.github.com/images/dojocat.jpg  \u0022The Dojocat\u0022\r\n\u0060\u0060\u0060\r\n\r\nHere\u0027s our logo (hover to see the title text):\r\n\r\nInline-style:\r\n![alt text](https://github.com/adam-p/markdown-here/raw/master/src/common/images/icon48.png \u0022Logo Title Text 1\u0022)\r\n\r\nReference-style:\r\n![alt text][logo]\r\n\r\n[logo]: https://github.com/adam-p/markdown-here/raw/master/src/common/images/icon48.png \u0022Logo Title Text 2\u0022\r\n\r\n![Minion](https://octodex.github.com/images/minion.png)\r\n![Stormtroopocat](https://octodex.github.com/images/stormtroopocat.jpg \u0022The Stormtroopocat\u0022)\r\n\r\nLike links, Images also have a footnote style syntax\r\n\r\n![Alt text][id]\r\n\r\nWith a reference later in the document defining the URL location:\r\n\r\n[id]: https://octodex.github.com/images/dojocat.jpg  \u0022The Dojocat\u0022\r\n\r\n------\r\n\r\n# [Footnotes](https://github.com/markdown-it/markdown-it-footnote)\r\n\r\n\u0060\u0060\u0060\r\nFootnote 1 link[^first].\r\n\r\nFootnote 2 link[^second].\r\n\r\nInline footnote^[Text of inline footnote] definition.\r\n\r\nDuplicated footnote reference[^second].\r\n\r\n[^first]: Footnote **can have markup**\r\n\r\n    and multiple paragraphs.\r\n\r\n[^second]: Footnote text.\r\n\u0060\u0060\u0060\r\n\r\nFootnote 1 link[^first].\r\n\r\nFootnote 2 link[^second].\r\n\r\nInline footnote^[Text of inline footnote] definition.\r\n\r\nDuplicated footnote reference[^second].\r\n\r\n[^first]: Footnote **can have markup**\r\n\r\n    and multiple paragraphs.\r\n\r\n[^second]: Footnote text.\r\n\r\n------\r\n\r\n# Code and Syntax Highlighting\r\n\r\n\u0060\u0060\u0060\r\nInline \u0060code\u0060 has \u0060back-ticks around\u0060 it.\r\n\u0060\u0060\u0060\r\n\r\nInline \u0060code\u0060 has \u0060back-ticks around\u0060 it.\r\n\r\n\u0060\u0060\u0060c#\r\nusing System.IO.Compression;\r\n\r\n#pragma warning disable 414, 3021\r\n\r\nnamespace MyApplication\r\n{\r\n    [Obsolete(\u0022...\u0022)]\r\n    class Program : IInterface\r\n    {\r\n        public static List\u003Cint\u003E JustDoIt(int count)\r\n        {\r\n            Console.WriteLine($\u0022Hello {Name}!\u0022);\r\n            return new List\u003Cint\u003E(new int[] { 1, 2, 3 })\r\n        }\r\n    }\r\n}\r\n\u0060\u0060\u0060\r\n\r\n\u0060\u0060\u0060css\r\n@font-face {\r\n  font-family: Chunkfive; src: url(\u0027Chunkfive.otf\u0027);\r\n}\r\n\r\nbody, .usertext {\r\n  color: #F0F0F0; background: #600;\r\n  font-family: Chunkfive, sans;\r\n}\r\n\r\n@import url(print.css);\r\n@media print {\r\n  a[href^=http]::after {\r\n    content: attr(href)\r\n  }\r\n}\r\n\u0060\u0060\u0060\r\n\r\n\u0060\u0060\u0060javascript\r\nfunction $initHighlight(block, cls) {\r\n  try {\r\n    if (cls.search(/\\bno\\-highlight\\b/) != -1)\r\n      return process(block, true, 0x0F) \u002B\r\n             \u0060 class=\u0022${cls}\u0022\u0060;\r\n  } catch (e) {\r\n    /* handle exception */\r\n  }\r\n  for (var i = 0 / 2; i \u003C classes.length; i\u002B\u002B) {\r\n    if (checkCondition(classes[i]) === undefined)\r\n      console.log(\u0027undefined\u0027);\r\n  }\r\n}\r\n\r\nexport  $initHighlight;\r\n\u0060\u0060\u0060\r\n\r\n\u0060\u0060\u0060php\r\nrequire_once \u0027Zend/Uri/Http.php\u0027;\r\n\r\nnamespace Location\\Web;\r\n\r\ninterface Factory\r\n{\r\n    static function _factory();\r\n}\r\n\r\nabstract class URI extends BaseURI implements Factory\r\n{\r\n    abstract function test();\r\n\r\n    public static $st1 = 1;\r\n    const ME = \u0022Yo\u0022;\r\n    var $list = NULL;\r\n    private $var;\r\n\r\n    /**\r\n     * Returns a URI\r\n     *\r\n     * @return URI\r\n     */\r\n    static public function _factory($stats = array(), $uri = \u0027http\u0027)\r\n    {\r\n        echo __METHOD__;\r\n        $uri = explode(\u0027:\u0027, $uri, 0b10);\r\n        $schemeSpecific = isset($uri[1]) ? $uri[1] : \u0027\u0027;\r\n        $desc = \u0027Multi\r\nline description\u0027;\r\n\r\n        // Security check\r\n        if (!ctype_alnum($scheme)) {\r\n            throw new Zend_Uri_Exception(\u0027Illegal scheme\u0027);\r\n        }\r\n\r\n        $this-\u003Evar = 0 - self::$st;\r\n        $this-\u003Elist = list(Array(\u00221\u0022=\u003E 2, 2=\u003Eself::ME, 3 =\u003E \\Location\\Web\\URI::class));\r\n\r\n        return [\r\n            \u0027uri\u0027   =\u003E $uri,\r\n            \u0027value\u0027 =\u003E null,\r\n        ];\r\n    }\r\n}\r\n\r\necho URI::ME . URI::$st1;\r\n\r\n__halt_compiler () ; datahere\r\ndatahere\r\ndatahere */\r\ndatahere\r\n\u0060\u0060\u0060\r\n\r\n------\r\n\r\n# Tables\r\n\r\n\u0060\u0060\u0060\r\nColons can be used to align columns.\r\n\r\n| Tables        | Are           | Cool  |\r\n| ------------- |:-------------:| -----:|\r\n| col 3 is      | right-aligned | $1600 |\r\n| col 2 is      | centered      |   $12 |\r\n| zebra stripes | are neat      |    $1 |\r\n\r\nThere must be at least 3 dashes separating each header cell.\r\nThe outer pipes (|) are optional, and you don\u0027t need to make the\r\nraw Markdown line up prettily. You can also use inline Markdown.\r\n\r\nMarkdown | Less | Pretty\r\n--- | --- | ---\r\n*Still* | \u0060renders\u0060 | **nicely**\r\n1 | 2 | 3\r\n\r\n| First Header  | Second Header |\r\n| ------------- | ------------- |\r\n| Content Cell  | Content Cell  |\r\n| Content Cell  | Content Cell  |\r\n\r\n| Command | Description |\r\n| --- | --- |\r\n| git status | List all new or modified files |\r\n| git diff | Show file differences that haven\u0027t been staged |\r\n\r\n| Command | Description |\r\n| --- | --- |\r\n| \u0060git status\u0060 | List all *new or modified* files |\r\n| \u0060git diff\u0060 | Show file differences that **haven\u0027t been** staged |\r\n\r\n| Left-aligned | Center-aligned | Right-aligned |\r\n| :---         |     :---:      |          ---: |\r\n| git status   | git status     | git status    |\r\n| git diff     | git diff       | git diff      |\r\n\r\n| Name     | Character |\r\n| ---      | ---       |\r\n| Backtick | \u0060         |\r\n| Pipe     | \\|        |\r\n\u0060\u0060\u0060\r\n\r\nColons can be used to align columns.\r\n\r\n| Tables        | Are           | Cool  |\r\n| ------------- |:-------------:| -----:|\r\n| col 3 is      | right-aligned | $1600 |\r\n| col 2 is      | centered      |   $12 |\r\n| zebra stripes | are neat      |    $1 |\r\n\r\nThere must be at least 3 dashes separating each header cell.\r\nThe outer pipes (|) are optional, and you don\u0027t need to make the\r\nraw Markdown line up prettily. You can also use inline Markdown.\r\n\r\nMarkdown | Less | Pretty\r\n--- | --- | ---\r\n*Still* | \u0060renders\u0060 | **nicely**\r\n1 | 2 | 3\r\n\r\n| First Header  | Second Header |\r\n| ------------- | ------------- |\r\n| Content Cell  | Content Cell  |\r\n| Content Cell  | Content Cell  |\r\n\r\n| Command | Description |\r\n| --- | --- |\r\n| git status | List all new or modified files |\r\n| git diff | Show file differences that haven\u0027t been staged |\r\n\r\n| Command | Description |\r\n| --- | --- |\r\n| \u0060git status\u0060 | List all *new or modified* files |\r\n| \u0060git diff\u0060 | Show file differences that **haven\u0027t been** staged |\r\n\r\n| Left-aligned | Center-aligned | Right-aligned |\r\n| :---         |     :---:      |          ---: |\r\n| git status   | git status     | git status    |\r\n| git diff     | git diff       | git diff      |\r\n\r\n| Name     | Character |\r\n| ---      | ---       |\r\n| Backtick | \u0060         |\r\n| Pipe     | \\|        |\r\n\r\n------\r\n\r\n# Blockquotes\r\n\r\n\u0060\u0060\u0060\r\n\u003E Blockquotes are very handy in email to emulate reply text.\r\n\u003E This line is part of the same quote.\r\n\r\nQuote break.\r\n\r\n\u003E This is a very long line that will still be quoted properly when it wraps. Oh boy let\u0027s keep writing to make sure this is long enough to actually wrap for everyone. Oh, you can *put* **Markdown** into a blockquote.\r\n\r\n\u003E Blockquotes can also be nested...\r\n\u003E\u003E ...by using additional greater-than signs right next to each other...\r\n\u003E \u003E \u003E ...or with spaces between arrows.\r\n\u0060\u0060\u0060\r\n\r\n\u003E Blockquotes are very handy in email to emulate reply text.\r\n\u003E This line is part of the same quote.\r\n\r\nQuote break.\r\n\r\n\u003E This is a very long line that will still be quoted properly when it wraps. Oh boy let\u0027s keep writing to make sure this is long enough to actually wrap for everyone. Oh, you can *put* **Markdown** into a blockquote.\r\n\r\n\u003E Blockquotes can also be nested...\r\n\u003E\u003E ...by using additional greater-than signs right next to each other...\r\n\u003E \u003E \u003E ...or with spaces between arrows.\r\n\r\n------\r\n\r\n# Inline HTML\r\n\r\n\u0060\u0060\u0060\r\n\u003Cdl\u003E\r\n  \u003Cdt\u003EDefinition list\u003C/dt\u003E\r\n  \u003Cdd\u003EIs something people use sometimes.\u003C/dd\u003E\r\n\r\n  \u003Cdt\u003EMarkdown in HTML\u003C/dt\u003E\r\n  \u003Cdd\u003EDoes *not* work **very** well. Use HTML \u003Cem\u003Etags\u003C/em\u003E.\u003C/dd\u003E\r\n\u003C/dl\u003E\r\n\u0060\u0060\u0060\r\n\r\n\u003Cdl\u003E\r\n  \u003Cdt\u003EDefinition list\u003C/dt\u003E\r\n  \u003Cdd\u003EIs something people use sometimes.\u003C/dd\u003E\r\n\r\n  \u003Cdt\u003EMarkdown in HTML\u003C/dt\u003E\r\n  \u003Cdd\u003EDoes *not* work **very** well. Use HTML \u003Cem\u003Etags\u003C/em\u003E.\u003C/dd\u003E\r\n\u003C/dl\u003E\r\n\r\n------\r\n\r\n# Horizontal Rules\r\n\r\n\u0060\u0060\u0060\r\nThree or more...\r\n\r\n---\r\n\r\nHyphens\r\n\r\n***\r\n\r\nAsterisks\r\n\r\n___\r\n\r\nUnderscores\r\n\u0060\u0060\u0060\r\n\r\nThree or more...\r\n\r\n---\r\n\r\nHyphens\r\n\r\n***\r\n\r\nAsterisks\r\n\r\n___\r\n\r\nUnderscores\r\n\r\n------\r\n\r\n"
    },
    {
      "FileName": "second-post.md",
      "Title": "Second Post",
      "Date": "2024-10-01T12:00:00",
      "Tags": [
        "test",
        "hello"
      ],
      "Content": "---\r\ntitle: \u0022Second Post\u0022\r\ndate: 2024-10-01 12:00:00\r\ntags: [test, hello]\r\n---\r\n\r\nLorem ipsum dolor sit amet, consectetur adipiscing elit. Duis vitae mi molestie, venenatis arcu nec, bibendum erat. In scelerisque mauris sed diam imperdiet pellentesque. Suspendisse imperdiet mauris ac justo fermentum aliquam. Donec luctus magna vitae nisi congue congue. Pellentesque non sollicitudin felis, eu condimentum nisi. Nullam eu cursus dui. Vestibulum gravida finibus ex in feugiat. Maecenas interdum iaculis purus. Pellentesque porttitor tellus a magna semper consequat. Sed ac dolor vel augue commodo varius. Cras nulla orci, vestibulum in risus vel, accumsan tincidunt nulla. Ut fringilla pretium mollis. Class aptent taciti sociosqu ad litora torquent per conubia nostra, per inceptos himenaeos. Vivamus feugiat mattis dui a tincidunt. Cras ac viverra ante.\r\n\r\nPellentesque sit amet lectus est. Praesent urna ex, sagittis non ullamcorper sit amet, gravida mattis erat. Aliquam vestibulum ullamcorper arcu. Etiam efficitur vel dui quis volutpat. Aliquam erat volutpat. Pellentesque sem est, maximus eu enim at, posuere bibendum tellus. Curabitur vel lacinia elit. Nullam est ex, imperdiet eu iaculis hendrerit, finibus eu sapien. Aenean quis tincidunt lacus.\r\n\r\nNunc imperdiet nulla non semper fringilla. Duis ac ante in risus bibendum hendrerit. Aenean rhoncus diam vel nulla semper accumsan. Donec finibus leo lorem, vitae auctor libero varius in. Phasellus ultrices rutrum est, eget porttitor augue dignissim a. Vestibulum ante ipsum primis in faucibus orci luctus et ultrices posuere cubilia curae; Quisque pharetra non metus ut efficitur. Cras maximus neque vitae urna interdum, sed gravida nisi laoreet. Etiam rutrum, erat vel bibendum molestie, urna tortor pharetra dui, ornare ornare massa nisi id diam.\r\n\r\nCras blandit odio augue, vel porttitor justo porttitor in. Vestibulum sit amet lorem turpis. In hendrerit nisl vel feugiat porttitor. Mauris tellus ante, fermentum vestibulum facilisis et, suscipit in est. Vivamus ultrices eros vel magna gravida finibus ut at dui. Vestibulum sit amet risus elit. Praesent vel massa sit amet erat congue venenatis.\r\n\r\nPellentesque sed tempus arcu, tristique condimentum nisl. Nunc in porta ante, a elementum felis. Cras vitae erat lacus. Nam turpis elit, dignissim non ligula eu, fermentum dictum arcu. Proin in erat ac velit viverra fermentum id nec eros. Quisque id vehicula diam, ac laoreet felis. Aliquam nec enim id ante venenatis consequat. Sed eu nisl quis neque tincidunt pretium nec finibus dolor. Suspendisse dapibus ex non iaculis euismod. Proin id neque urna. Etiam eget est pulvinar libero suscipit commodo nec sit amet dolor. In hac habitasse platea dictumst. Etiam vulputate arcu ut tincidunt posuere. Phasellus auctor dui dignissim auctor varius. Praesent vel enim elementum, porttitor augue nec, eleifend velit."
    },
    {
      "FileName": "first-post.md",
      "Title": "Hello world!",
      "Date": "2023-10-01T12:00:00",
      "Tags": [
        "test",
        "hello"
      ],
      "Content": "---\r\ntitle: \u0022Hello world!\u0022\r\ndate: 2023-10-01 12:00:00\r\ntags: [test, hello]\r\n---\r\n\r\n\r\n\r\n## Hello world!\r\n\r\n### This is my first post\r\n\r\n"
    }
  ]
}